ikomia/__init__.py
ikomia/core/__init__.py
ikomia/core/auth.py
ikomia/core/config.py
ikomia/core/config.yaml
ikomia/core/config_template.yaml
ikomia/core/pycore.so
ikomia/core/task.py
ikomia/dataio/__init__.py
ikomia/dataio/pydataio.so
ikomia/dataprocess/__init__.py
ikomia/dataprocess/datadictIO.py
ikomia/dataprocess/pydataprocess.so
ikomia/dataprocess/registry.py
ikomia/dataprocess/tile_processing.py
ikomia/dataprocess/workflow.py
ikomia/dnn/__init__.py
ikomia/dnn/dataset.py
ikomia/dnn/datasetio.py
ikomia/dnn/dnntrain.py
ikomia/dnn/monitoring.py
ikomia/dnn/torch/__init__.py
ikomia/dnn/torch/datasetmapper.py
ikomia/dnn/torch/models.py
ikomia/dnn/torch/utils.py
ikomia/lib/libOpenCL.so.1
ikomia/lib/libQt5Core.so.5
ikomia/lib/libQt5DBus.so.5
ikomia/lib/libQt5Gui.so.5
ikomia/lib/libQt5Network.so.5
ikomia/lib/libQt5Sql.so.5
ikomia/lib/libQt5Svg.so.5
ikomia/lib/libQt5Widgets.so.5
ikomia/lib/libQt5XcbQpa.so.5
ikomia/lib/libXau.so.6
ikomia/lib/libXcomposite.so.1
ikomia/lib/libXcursor.so.1
ikomia/lib/libXdamage.so.1
ikomia/lib/libXdmcp.so.6
ikomia/lib/libXext.so.6
ikomia/lib/libXfixes.so.3
ikomia/lib/libXi.so.6
ikomia/lib/libXinerama.so.1
ikomia/lib/libXrandr.so.2
ikomia/lib/libXrender.so.1
ikomia/lib/libaom.so.3
ikomia/lib/libatk-1.0.so.0
ikomia/lib/libatk-bridge-2.0.so.0
ikomia/lib/libatspi.so.0
ikomia/lib/libavcodec.so.58
ikomia/lib/libavformat.so.58
ikomia/lib/libavutil.so.56
ikomia/lib/libblkid.so.1
ikomia/lib/libbluray.so.2
ikomia/lib/libboost_filesystem.so.1.88.0
ikomia/lib/libboost_python39.so.1.88.0
ikomia/lib/libbrotlicommon.so.1
ikomia/lib/libbrotlidec.so.1
ikomia/lib/libbsd.so.0
ikomia/lib/libbz2.so.1.0
ikomia/lib/libcairo-gobject.so.2
ikomia/lib/libcairo.so.2
ikomia/lib/libcap.so.2
ikomia/lib/libchromaprint.so.1
ikomia/lib/libcodec2.so.1.0
ikomia/lib/libdatrie.so.1
ikomia/lib/libdav1d.so.5
ikomia/lib/libdbus-1.so.3
ikomia/lib/libdeflate.so.0
ikomia/lib/libdw.so.1
ikomia/lib/libelf.so.1
ikomia/lib/libepoxy.so.0
ikomia/lib/libffi.so.8
ikomia/lib/libgcrypt.so.20
ikomia-0.15.0.dist-info/LICENSE.md
ikomia-0.15.0.dist-info/METADATA
ikomia-0.15.0.dist-info/WHEEL
ikomia-0.15.0.dist-info/top_level.txt
ikomia-0.15.0.dist-info/RECORD
