Metadata-Version: 2.1
Name: ikomia
Version: 0.15.0
Summary: Ikomia Python API for Computer Vision workflow and plugin integration in Ikomia Studio
Home-page: https://github.com/Ikomia-dev/IkomiaApi
Author: Ikomia SAS
Author-email: contact@ikomia.com
License: Apache 2.0
Keywords: computer vision,deep learning,workflow
Requires-Python: >=3.8
License-File: LICENSE.md
Requires-Dist: cython
Requires-Dist: setuptools==73.0.1
Requires-Dist: numpy<3.0,>=2.0
Requires-Dist: requests<3.0,>=2.28.0
Requires-Dist: mlflow<3.0,>=2.17.2
Requires-Dist: tensorboard<3.0,>=2.5.0
Requires-Dist: Pillow>=8.1.0
Requires-Dist: tqdm<5.0,>=4.41.0
Requires-Dist: matplotlib<4.0,>=3.4.3
Requires-Dist: python-dotenv>=0.18.0
Requires-Dist: pyyaml
Requires-Dist: semver<4.0,>=3.0.1
